License
README.md
ckanclient/__init__.py
ckanclient/auth.py
ckanclient/text.py
ckanclient/upload.py
ckan_client-0.1.1.dist-info/WHEEL
ckan_client-0.1.1.dist-info/METADATA
ckan_client-0.1.1.dist-info/RECORD
