Metadata-Version: 2.1
Name: ckan-client
Version: 0.1.1
Summary: CKAN Python SDK for CKAN3 instances with CKAN3 cloud storage.
Home-page: https://github.com/datopian/ckan-client-py
License: MIT
Keywords: ckan,api,upload,cloud
Author: Datopian
Author-email: contact@datopian.com
Requires-Python: >=3.6,<4.0
Classifier: Development Status :: 3 - Alpha
Classifier: License :: OSI Approved :: MIT License
Classifier: Programming Language :: Python :: 3
Classifier: Programming Language :: Python :: 3.6
Classifier: Programming Language :: Python :: 3.7
Classifier: Programming Language :: Python :: 3.8
Requires-Dist: frictionless-ckan-mapper (>=1.0.6,<2.0.0)
Requires-Dist: requests (>=2.24.0,<3.0.0)
